awss/__init__.py
awss/__main__.py
awss/awsc.py
awss/colors.py
awss/core.py
awss/debg.py
awss-0.9.13.dist-info/DESCRIPTION.rst
awss-0.9.13.dist-info/METADATA
awss-0.9.13.dist-info/RECORD
awss-0.9.13.dist-info/WHEEL
awss-0.9.13.dist-info/entry_points.txt
awss-0.9.13.dist-info/metadata.json
awss-0.9.13.dist-info/top_level.txt
