Metadata-Version: 2.0
Name: awss
Version: 0.9.13
Summary: AWS Shortcuts for Command-Line Instance Control
Home-page: https://github.com/robertpeteuil/aws-shortcuts
Author: Robert Peteuil
Author-email: robert.s.peteuil@gmail.com
License: GNU General Public License v3 (GPLv3)
Download-URL: https://pypi.python.org/pypi/awss/
Keywords: AWS EC2 instance control ssh
Platform: any
Classifier: Development Status :: 5 - Production/Stable
Classifier: Environment :: Console
Classifier: Intended Audience :: System Administrators
Classifier: Intended Audience :: Information Technology
Classifier: Intended Audience :: Developers
Classifier: License :: OSI Approved :: GNU General Public License v3 (GPLv3)
Classifier: Natural Language :: English
Classifier: Operating System :: MacOS :: MacOS X
Classifier: Operating System :: POSIX
Classifier: Operating System :: Microsoft :: Windows
Classifier: Programming Language :: Python
Classifier: Programming Language :: Python :: 2
Classifier: Programming Language :: Python :: 2.7
Classifier: Programming Language :: Python :: 3
Classifier: Programming Language :: Python :: 3.3
Classifier: Programming Language :: Python :: 3.4
Classifier: Programming Language :: Python :: 3.5
Classifier: Programming Language :: Python :: 3.6
Classifier: Topic :: System :: Distributed Computing
Classifier: Topic :: System :: Systems Administration
Requires-Dist: boto3 (>=1.4)
Requires-Dist: colorama
Requires-Dist: future (>=0.14)
